setup.py
ggshmysql/__init__.py
ggshmysql/load.py
ggshmysql.egg-info/PKG-INFO
ggshmysql.egg-info/SOURCES.txt
ggshmysql.egg-info/dependency_links.txt
ggshmysql.egg-info/not-zip-safe
ggshmysql.egg-info/requires.txt
ggshmysql.egg-info/top_level.txt