Metadata-Version: 1.0
Name: ggshmysql
Version: 0.13
Summary: Data exchange from Google Sheet to MySQL database, fixed encoding issue
Home-page: https://github.com/ghao2/ggshmysql
Author: Guoxuan Hao
Author-email: haoguoxuan@gmail.com
License: MIT
Platform: UNKNOWN
